setup.cfg
setup.py
url_matchers.py
url_matchers.egg-info/PKG-INFO
url_matchers.egg-info/SOURCES.txt
url_matchers.egg-info/dependency_links.txt
url_matchers.egg-info/requires.txt
url_matchers.egg-info/top_level.txt