Metadata-Version: 1.0
Name: url-matchers
Version: 0.0.7
Summary: Url matchers for PyHamcrest
Home-page: https://github.com/alexjg/url-matchers
Author: Alex Good
Author-email: alex@makerlabs.co.uk
License: UNKNOWN
Platform: UNKNOWN
